{"currentTime":1717351822104,"commandStatsInstance":{"mostCommandsUsedMonth":{},"mostCommandsUsedEver":{}},"managerStatsInstance":{"ticketsDay":0,"ticketsMonth":0,"ticketsEver":0,"temporaryChannelsMonth":0,"temporaryChannelsEver":0,"musicPlayedMonth":0,"musicPlayedEver":0,"musicTimePlayedDay":0,"musicTimePlayedMonth":0},"memberStatsInstance":{"bestUserCallTimeMonth":{},"bestUserCallTimeEver":{},"bestUserTextCounterMonth":{},"bestUserTextCounterEver":{},"bestUserCommandsUsedMonth":{},"bestUserCommandsUsedEver":{}},"serverStatsInstance":{"memberJoinDay":0,"memberJoinMonth":0,"memberJoinEver":0,"memberLeaveDay":0,"memberLeaveMonth":0,"memberLeaveEver":0},"textChannelStatsInstance":{"usedTextChannelIdMonth":{},"usedTextChannelIdEver":{},"textCounterDay":0,"textCounterMonth":0,"textCounterEver":0},"voiceChannelStatsInstance":{"usedVoiceChannelIdMonth":{},"usedVoiceChannelIdEver":{},"callTimeDay":0,"callTimeMonth":0,"callTimeEver":0},"memberJoinVoiceTime":{}}